karabo_utidserver/__init__.py
karabo_utidserver/_version.py
karabo_utidserver/utid_server.py
karabo_utidserver/tests/__init__.py
karabo_utidserver/tests/property_naming_test.py
karabo_utidserver/tests/sub_module_test.py
karabo_utidserver/tests/test_utidserver.py
karabo_utidserver-3.0.2.dist-info/licenses/LICENSE.md
karabo_utidserver-3.0.2.dist-info/METADATA
karabo_utidserver-3.0.2.dist-info/WHEEL
karabo_utidserver-3.0.2.dist-info/entry_points.txt
karabo_utidserver-3.0.2.dist-info/top_level.txt
karabo_utidserver-3.0.2.dist-info/RECORD
