Metadata-Version: 2.4
Name: karabo-utidserver
Version: 3.0.2
Summary: A provider of Universal Unique Time IDs, UTIDs
Author-email: "S. Hauf" <steffen.hauf@xfel.eu>
Maintainer-email: "S. Hauf" <steffen.hauf@xfel.eu>
License: Mozilla Public License Version 2.0
Requires-Python: >=3.12
License-File: LICENSE.md
Requires-Dist: karabo[karathon]
Provides-Extra: test
Requires-Dist: pytest; extra == "test"
Requires-Dist: coverage; extra == "test"
Dynamic: license-file
